{
  "annotations": {
    "list": [
      {
        "builtIn": 1,
        "datasource": "-- Grafana --",
        "enable": true,
        "hide": true,
        "iconColor": "rgba(0, 211, 255, 1)",
        "name": "Annotations & Alerts",
        "type": "dashboard"
      }
    ]
  },
  "editable": true,
  "gnetId": null,
  "graphTooltip": 0,
  "id": 1,
  "links": [],
  "panels": [
    {
      "datasource": null,
      "fieldConfig": {
        "defaults": {
          "color": {
            "mode": "thresholds"
          },
          "mappings": [
            {
              "options": {
                "0": {
                  "color": "dark-green",
                  "index": 0,
                  "text": "safe"
                }
              },
              "type": "value"
            },
            {
              "options": {
                "from": 1,
                "result": {
                  "color": "dark-red",
                  "index": 1,
                  "text": "not safe"
                },
                "to": 3
              },
              "type": "range"
            }
          ],
          "thresholds": {
            "mode": "absolute",
            "steps": [
              {
                "color": "green",
                "value": null
              },
              {
                "color": "dark-red",
                "value": 1
              }
            ]
          }
        },
        "overrides": []
      },
      "gridPos": {
        "h": 8,
        "w": 8,
        "x": 8,
        "y": 0
      },
      "id": 2,
      "interval": "5s",
      "options": {
        "colorMode": "value",
        "graphMode": "none",
        "justifyMode": "auto",
        "orientation": "auto",
        "reduceOptions": {
          "calcs": [
            "last"
          ],
          "fields": "/^house\\-alert$/",
          "values": false
        },
        "text": {},
        "textMode": "auto"
      },
      "pluginVersion": "8.0.6",
      "targets": [
        {
          "exemplar": true,
          "expr": "is_safe{}",
          "interval": "",
          "legendFormat": "{{ app }}",
          "refId": "A"
        }
      ],
      "title": "Total Safety",
      "transparent": true,
      "type": "stat"
    },
    {
      "datasource": null,
      "gridPos": {
        "h": 1,
        "w": 24,
        "x": 0,
        "y": 8
      },
      "id": 22,
      "title": "Current Safety Status",
      "type": "row"
    },
    {
      "datasource": null,
      "description": "Is Living Room Currently\n Safe",
      "fieldConfig": {
        "defaults": {
          "color": {
            "mode": "thresholds"
          },
          "mappings": [
            {
              "options": {
                "0": {
                  "color": "dark-green",
                  "index": 0,
                  "text": "safe"
                },
                "1": {
                  "color": "dark-red",
                  "index": 1,
                  "text": "not safe"
                }
              },
              "type": "value"
            }
          ],
          "thresholds": {
            "mode": "absolute",
            "steps": [
              {
                "color": "green",
                "value": null
              },
              {
                "color": "dark-red",
                "value": 1
              }
            ]
          }
        },
        "overrides": []
      },
      "gridPos": {
        "h": 6,
        "w": 4,
        "x": 0,
        "y": 9
      },
      "id": 10,
      "interval": "5s",
      "options": {
        "reduceOptions": {
          "calcs": [
            "lastNotNull"
          ],
          "fields": "/^house\\-alert$/",
          "values": false
        },
        "showThresholdLabels": false,
        "showThresholdMarkers": false,
        "text": {}
      },
      "pluginVersion": "8.0.6",
      "targets": [
        {
          "exemplar": true,
          "expr": "livingroom_break",
          "interval": "",
          "legendFormat": "{{ app }}",
          "refId": "A"
        }
      ],
      "title": "Living Room Window",
      "type": "gauge"
    },
    {
      "datasource": null,
      "fieldConfig": {
        "defaults": {
          "color": {
            "mode": "thresholds"
          },
          "mappings": [
            {
              "options": {
                "0": {
                  "color": "dark-green",
                  "index": 0,
                  "text": "safe"
                },
                "1": {
                  "color": "dark-red",
                  "index": 1,
                  "text": "not safe"
                }
              },
              "type": "value"
            }
          ],
          "thresholds": {
            "mode": "absolute",
            "steps": [
              {
                "color": "green",
                "value": null
              },
              {
                "color": "dark-red",
                "value": 1
              }
            ]
          }
        },
        "overrides": []
      },
      "gridPos": {
        "h": 6,
        "w": 4,
        "x": 4,
        "y": 9
      },
      "id": 12,
      "interval": "5s",
      "options": {
        "reduceOptions": {
          "calcs": [
            "lastNotNull"
          ],
          "fields": "/^house\\-alert$/",
          "values": false
        },
        "showThresholdLabels": false,
        "showThresholdMarkers": false,
        "text": {}
      },
      "pluginVersion": "8.0.6",
      "targets": [
        {
          "exemplar": true,
          "expr": "bedroom_break",
          "interval": "",
          "legendFormat": "{{ app }}",
          "refId": "A"
        }
      ],
      "title": "Bed Room Window",
      "type": "gauge"
    },
    {
      "datasource": null,
      "fieldConfig": {
        "defaults": {
          "color": {
            "mode": "thresholds"
          },
          "mappings": [
            {
              "options": {
                "0": {
                  "color": "dark-green",
                  "index": 0,
                  "text": "safe"
                },
                "1": {
                  "color": "dark-red",
                  "index": 1,
                  "text": "not safe"
                }
              },
              "type": "value"
            }
          ],
          "thresholds": {
            "mode": "absolute",
            "steps": [
              {
                "color": "green",
                "value": null
              },
              {
                "color": "dark-red",
                "value": 1
              }
            ]
          }
        },
        "overrides": []
      },
      "gridPos": {
        "h": 6,
        "w": 4,
        "x": 8,
        "y": 9
      },
      "id": 14,
      "interval": "5s",
      "options": {
        "reduceOptions": {
          "calcs": [
            "lastNotNull"
          ],
          "fields": "/^house\\-alert$/",
          "values": false
        },
        "showThresholdLabels": false,
        "showThresholdMarkers": false,
        "text": {}
      },
      "pluginVersion": "8.0.6",
      "targets": [
        {
          "exemplar": true,
          "expr": "garden_break",
          "interval": "",
          "legendFormat": "{{ app }}",
          "refId": "A"
        }
      ],
      "title": "Garden",
      "type": "gauge"
    },
    {
      "datasource": null,
      "fieldConfig": {
        "defaults": {
          "color": {
            "mode": "thresholds"
          },
          "mappings": [],
          "thresholds": {
            "mode": "absolute",
            "steps": [
              {
                "color": "dark-blue",
                "value": null
              }
            ]
          }
        },
        "overrides": []
      },
      "gridPos": {
        "h": 6,
        "w": 4,
        "x": 12,
        "y": 9
      },
      "id": 16,
      "options": {
        "colorMode": "value",
        "graphMode": "none",
        "justifyMode": "auto",
        "orientation": "auto",
        "reduceOptions": {
          "calcs": [
            "lastNotNull"
          ],
          "fields": "/^house\\-alert$/",
          "values": false
        },
        "text": {},
        "textMode": "auto"
      },
      "pluginVersion": "8.0.6",
      "targets": [
        {
          "exemplar": true,
          "expr": "number_of_active_devices",
          "interval": "",
          "legendFormat": "{{ app }}",
          "refId": "A"
        }
      ],
      "title": "Active Devices",
      "type": "stat"
    },
    {
      "datasource": null,
      "fieldConfig": {
        "defaults": {
          "color": {
            "fixedColor": "dark-yellow",
            "mode": "fixed"
          },
          "mappings": [],
          "thresholds": {
            "mode": "absolute",
            "steps": [
              {
                "color": "dark-blue",
                "value": null
              }
            ]
          }
        },
        "overrides": []
      },
      "gridPos": {
        "h": 6,
        "w": 4,
        "x": 16,
        "y": 9
      },
      "id": 6,
      "interval": "5s",
      "options": {
        "colorMode": "value",
        "graphMode": "none",
        "justifyMode": "auto",
        "orientation": "auto",
        "reduceOptions": {
          "calcs": [
            "lastNotNull"
          ],
          "fields": "",
          "values": false
        },
        "text": {},
        "textMode": "auto"
      },
      "pluginVersion": "8.0.6",
      "targets": [
        {
          "exemplar": true,
          "expr": "num_of_total_burglaries",
          "interval": "",
          "legendFormat": "{{ app }}",
          "refId": "A"
        }
      ],
      "title": "Number of Burglaries",
      "type": "stat"
    },
    {
      "datasource": null,
      "fieldConfig": {
        "defaults": {
          "color": {
            "fixedColor": "dark-red",
            "mode": "fixed"
          },
          "mappings": [],
          "thresholds": {
            "mode": "absolute",
            "steps": [
              {
                "color": "green",
                "value": null
              }
            ]
          }
        },
        "overrides": []
      },
      "gridPos": {
        "h": 6,
        "w": 4,
        "x": 20,
        "y": 9
      },
      "id": 8,
      "interval": "5s",
      "options": {
        "colorMode": "value",
        "graphMode": "none",
        "justifyMode": "auto",
        "orientation": "auto",
        "reduceOptions": {
          "calcs": [
            "lastNotNull"
          ],
          "fields": "",
          "values": false
        },
        "text": {},
        "textMode": "auto"
      },
      "pluginVersion": "8.0.6",
      "targets": [
        {
          "exemplar": true,
          "expr": "num_of_breaks",
          "interval": "",
          "legendFormat": "{{ app }}",
          "refId": "A"
        }
      ],
      "title": "Number of Actual Breaks",
      "type": "stat"
    },
    {
      "datasource": null,
      "fieldConfig": {
        "defaults": {
          "color": {
            "mode": "thresholds"
          },
          "mappings": [
            {
              "options": {
                "0": {
                  "color": "text",
                  "index": 0,
                  "text": "OFF"
                },
                "1": {
                  "color": "dark-yellow",
                  "index": 1,
                  "text": "ON"
                }
              },
              "type": "value"
            }
          ],
          "thresholds": {
            "mode": "absolute",
            "steps": [
              {
                "color": "green",
                "value": null
              }
            ]
          }
        },
        "overrides": []
      },
      "gridPos": {
        "h": 3,
        "w": 4,
        "x": 0,
        "y": 15
      },
      "id": 30,
      "interval": "5s",
      "options": {
        "colorMode": "value",
        "graphMode": "none",
        "justifyMode": "auto",
        "orientation": "auto",
        "reduceOptions": {
          "calcs": [
            "lastNotNull"
          ],
          "fields": "/^house\\-alert$/",
          "values": false
        },
        "text": {},
        "textMode": "value"
      },
      "pluginVersion": "8.0.6",
      "targets": [
        {
          "exemplar": true,
          "expr": "livingroom_break",
          "interval": "",
          "legendFormat": "{{ app }}",
          "refId": "A"
        }
      ],
      "title": "Living Room Light",
      "type": "stat"
    },
    {
      "datasource": null,
      "fieldConfig": {
        "defaults": {
          "color": {
            "mode": "thresholds"
          },
          "mappings": [
            {
              "options": {
                "0": {
                  "color": "text",
                  "index": 0,
                  "text": "OFF"
                },
                "1": {
                  "color": "dark-yellow",
                  "index": 1,
                  "text": "ON"
                }
              },
              "type": "value"
            }
          ],
          "thresholds": {
            "mode": "absolute",
            "steps": [
              {
                "color": "green",
                "value": null
              }
            ]
          }
        },
        "overrides": []
      },
      "gridPos": {
        "h": 3,
        "w": 4,
        "x": 4,
        "y": 15
      },
      "id": 32,
      "interval": "5s",
      "options": {
        "colorMode": "value",
        "graphMode": "none",
        "justifyMode": "auto",
        "orientation": "auto",
        "reduceOptions": {
          "calcs": [
            "lastNotNull"
          ],
          "fields": "/^house\\-alert$/",
          "values": false
        },
        "text": {},
        "textMode": "auto"
      },
      "pluginVersion": "8.0.6",
      "targets": [
        {
          "exemplar": true,
          "expr": "bedroom_break",
          "interval": "",
          "legendFormat": "{{ app }}",
          "refId": "A"
        }
      ],
      "title": "Bedroom Light",
      "type": "stat"
    },
    {
      "datasource": null,
      "fieldConfig": {
        "defaults": {
          "color": {
            "mode": "thresholds"
          },
          "mappings": [
            {
              "options": {
                "0": {
                  "color": "text",
                  "index": 0,
                  "text": "OFF"
                },
                "1": {
                  "color": "dark-yellow",
                  "index": 1,
                  "text": "ON"
                }
              },
              "type": "value"
            }
          ],
          "thresholds": {
            "mode": "absolute",
            "steps": [
              {
                "color": "green",
                "value": null
              }
            ]
          }
        },
        "overrides": []
      },
      "gridPos": {
        "h": 3,
        "w": 4,
        "x": 8,
        "y": 15
      },
      "id": 34,
      "interval": "5s",
      "options": {
        "colorMode": "value",
        "graphMode": "none",
        "justifyMode": "auto",
        "orientation": "auto",
        "reduceOptions": {
          "calcs": [
            "lastNotNull"
          ],
          "fields": "/^house\\-alert$/",
          "values": false
        },
        "text": {},
        "textMode": "auto"
      },
      "pluginVersion": "8.0.6",
      "targets": [
        {
          "exemplar": true,
          "expr": "garden_break",
          "interval": "",
          "legendFormat": "{{ app }}",
          "refId": "A"
        }
      ],
      "title": "Garden Lights",
      "type": "stat"
    },
    {
      "datasource": null,
      "fieldConfig": {
        "defaults": {
          "color": {
            "fixedColor": "dark-red",
            "mode": "fixed"
          },
          "mappings": [],
          "thresholds": {
            "mode": "absolute",
            "steps": [
              {
                "color": "green",
                "value": null
              }
            ]
          }
        },
        "overrides": []
      },
      "gridPos": {
        "h": 3,
        "w": 4,
        "x": 12,
        "y": 15
      },
      "id": 36,
      "options": {
        "colorMode": "value",
        "graphMode": "none",
        "justifyMode": "auto",
        "orientation": "auto",
        "reduceOptions": {
          "calcs": [
            "lastNotNull"
          ],
          "fields": "/^house\\-alert$/",
          "values": false
        },
        "text": {},
        "textMode": "auto"
      },
      "pluginVersion": "8.0.6",
      "targets": [
        {
          "exemplar": true,
          "expr": "number_of_defective_devices",
          "interval": "",
          "legendFormat": "{{ app }}",
          "refId": "A"
        }
      ],
      "title": "Defective Devices",
      "type": "stat"
    },
    {
      "collapsed": false,
      "datasource": null,
      "gridPos": {
        "h": 1,
        "w": 24,
        "x": 0,
        "y": 18
      },
      "id": 18,
      "panels": [],
      "title": "Statistics",
      "type": "row"
    },
    {
      "datasource": null,
      "fieldConfig": {
        "defaults": {
          "color": {
            "fixedColor": "dark-blue",
            "mode": "fixed"
          },
          "custom": {
            "axisLabel": "",
            "axisPlacement": "hidden",
            "axisSoftMax": 1,
            "axisSoftMin": 0,
            "barAlignment": 0,
            "drawStyle": "bars",
            "fillOpacity": 30,
            "gradientMode": "none",
            "hideFrom": {
              "legend": false,
              "tooltip": false,
              "viz": false
            },
            "lineInterpolation": "linear",
            "lineStyle": {
              "fill": "solid"
            },
            "lineWidth": 10,
            "pointSize": 10,
            "scaleDistribution": {
              "type": "linear"
            },
            "showPoints": "auto",
            "spanNulls": false,
            "stacking": {
              "group": "A",
              "mode": "none"
            },
            "thresholdsStyle": {
              "mode": "off"
            }
          },
          "mappings": [
            {
              "options": {
                "from": 0.1,
                "result": {
                  "color": "dark-red",
                  "index": 0,
                  "text": "Burglary"
                },
                "to": 3
              },
              "type": "range"
            }
          ],
          "thresholds": {
            "mode": "absolute",
            "steps": [
              {
                "color": "dark-blue",
                "value": null
              }
            ]
          }
        },
        "overrides": []
      },
      "gridPos": {
        "h": 4,
        "w": 24,
        "x": 0,
        "y": 19
      },
      "id": 20,
      "options": {
        "legend": {
          "calcs": [],
          "displayMode": "hidden",
          "placement": "bottom"
        },
        "tooltip": {
          "mode": "single"
        }
      },
      "targets": [
        {
          "exemplar": true,
          "expr": "is_safe",
          "interval": "",
          "legendFormat": "{{ app }}",
          "refId": "A"
        }
      ],
      "title": "Burglaries History",
      "type": "timeseries"
    },
    {
      "datasource": null,
      "fieldConfig": {
        "defaults": {
          "color": {
            "fixedColor": "light-green",
            "mode": "fixed"
          },
          "custom": {
            "axisLabel": "",
            "axisPlacement": "hidden",
            "barAlignment": 0,
            "drawStyle": "bars",
            "fillOpacity": 10,
            "gradientMode": "none",
            "hideFrom": {
              "legend": false,
              "tooltip": false,
              "viz": false
            },
            "lineInterpolation": "linear",
            "lineWidth": 10,
            "pointSize": 5,
            "scaleDistribution": {
              "type": "linear"
            },
            "showPoints": "auto",
            "spanNulls": false,
            "stacking": {
              "group": "A",
              "mode": "none"
            },
            "thresholdsStyle": {
              "mode": "off"
            }
          },
          "mappings": [],
          "thresholds": {
            "mode": "absolute",
            "steps": [
              {
                "color": "green",
                "value": null
              }
            ]
          }
        },
        "overrides": []
      },
      "gridPos": {
        "h": 3,
        "w": 12,
        "x": 0,
        "y": 23
      },
      "id": 24,
      "options": {
        "legend": {
          "calcs": [],
          "displayMode": "hidden",
          "placement": "bottom"
        },
        "tooltip": {
          "mode": "single"
        }
      },
      "targets": [
        {
          "exemplar": true,
          "expr": "garden_break",
          "interval": "",
          "legendFormat": "{{ app }}",
          "refId": "A"
        }
      ],
      "title": "Garden History",
      "type": "timeseries"
    },
    {
      "datasource": null,
      "fieldConfig": {
        "defaults": {
          "color": {
            "fixedColor": "light-purple",
            "mode": "fixed"
          },
          "custom": {
            "axisLabel": "",
            "axisPlacement": "hidden",
            "barAlignment": 0,
            "drawStyle": "bars",
            "fillOpacity": 10,
            "gradientMode": "opacity",
            "hideFrom": {
              "legend": false,
              "tooltip": false,
              "viz": false
            },
            "lineInterpolation": "linear",
            "lineWidth": 10,
            "pointSize": 5,
            "scaleDistribution": {
              "type": "linear"
            },
            "showPoints": "auto",
            "spanNulls": false,
            "stacking": {
              "group": "A",
              "mode": "none"
            },
            "thresholdsStyle": {
              "mode": "off"
            }
          },
          "mappings": [],
          "thresholds": {
            "mode": "absolute",
            "steps": [
              {
                "color": "green",
                "value": null
              }
            ]
          }
        },
        "overrides": []
      },
      "gridPos": {
        "h": 3,
        "w": 12,
        "x": 12,
        "y": 23
      },
      "id": 26,
      "options": {
        "legend": {
          "calcs": [],
          "displayMode": "hidden",
          "placement": "bottom"
        },
        "tooltip": {
          "mode": "none"
        }
      },
      "targets": [
        {
          "exemplar": true,
          "expr": "livingroom_break",
          "interval": "",
          "legendFormat": "{{ app }}",
          "refId": "A"
        }
      ],
      "title": "Living Room History",
      "type": "timeseries"
    },
    {
      "datasource": null,
      "fieldConfig": {
        "defaults": {
          "color": {
            "mode": "fixed"
          },
          "custom": {
            "axisLabel": "",
            "axisPlacement": "hidden",
            "barAlignment": 0,
            "drawStyle": "bars",
            "fillOpacity": 10,
            "gradientMode": "opacity",
            "hideFrom": {
              "legend": false,
              "tooltip": false,
              "viz": false
            },
            "lineInterpolation": "linear",
            "lineWidth": 10,
            "pointSize": 5,
            "scaleDistribution": {
              "type": "linear"
            },
            "showPoints": "auto",
            "spanNulls": false,
            "stacking": {
              "group": "A",
              "mode": "none"
            },
            "thresholdsStyle": {
              "mode": "off"
            }
          },
          "mappings": [],
          "thresholds": {
            "mode": "absolute",
            "steps": [
              {
                "color": "green",
                "value": null
              }
            ]
          }
        },
        "overrides": []
      },
      "gridPos": {
        "h": 3,
        "w": 12,
        "x": 0,
        "y": 26
      },
      "id": 28,
      "options": {
        "legend": {
          "calcs": [],
          "displayMode": "hidden",
          "placement": "bottom"
        },
        "tooltip": {
          "mode": "none"
        }
      },
      "targets": [
        {
          "exemplar": true,
          "expr": "bedroom_break",
          "interval": "",
          "legendFormat": "{{ app }}",
          "refId": "A"
        }
      ],
      "title": "Bedroom History",
      "type": "timeseries"
    }
  ],
  "refresh": "5s",
  "schemaVersion": 30,
  "style": "dark",
  "tags": [],
  "templating": {
    "list": []
  },
  "time": {
    "from": "now-5m",
    "to": "now"
  },
  "timepicker": {},
  "timezone": "",
  "title": "house Alert",
  "uid": "dGtUcdZ7k",
  "version": 15
}